rail/__init__.py
rail/control.py
rail/cpi.py
rail/impact.py
rail/likelihood.py
rail/risk.py
rail/threat_event.py
rail/threat_source.py
rail/tree.py
rail/vulnerability.py
RAIL-0.6.dist-info/LICENSE
RAIL-0.6.dist-info/METADATA
RAIL-0.6.dist-info/WHEEL
RAIL-0.6.dist-info/top_level.txt
RAIL-0.6.dist-info/RECORD
